{
    "format_version": "1.19.0",
    "minecraft:recipe_shaped": {
        "description": {
            "identifier": "betterend:silk_touch"
        },
        "tags": [
            "infusion_pedestal"
        ],
        "pattern": [
            "lel",
            "cbc",
            "lvl"
        ],
        "key": {
            "l": {
                "item": "minecraft:lapis_lazuli"
            },
            "e": {
                "item": "betterend:enchanted_petal"
            },
            "b": {
                "item": "minecraft:book"
            },
            "c": {
                "item": "minecraft:web"
            },
            "v": {
                "item": "betterend:eternal_crystal"
            }
        },
        "result": {
            "item": "betterend:silk_touch"
        }
    }
}