{
    "format_version": "1.19.0",
    "minecraft:recipe_shaped": {
        "description": {
            "identifier": "betterend:smaragdant_tiles"
        },
        "tags": [
            "crafting_table"
        ],
        "pattern": [
            "pp",
            "pp"
        ],
        "key": {
            "p": {
                "item": "betterend:smaragdant_polished"
            }
        },
        "result": {
            "item": "betterend:smaragdant_tiles",
            "count": 4
        }
    }
}